dorn/__init__.py
dorn/app.py
dorn/cli.py
dorn/gui_background.png
dorn/organisation_logo.png
dorn/shovel.ico
dorn-2.0.0.dist-info/entry_points.txt
dorn-2.0.0.dist-info/licenses/LICENSE
dorn-2.0.0.dist-info/WHEEL
dorn-2.0.0.dist-info/METADATA
dorn-2.0.0.dist-info/RECORD
