Metadata-Version: 2.4
Name: dorn
Version: 2.0.0
Summary: Close contact restrictions for radionuclide therapy patients
Author: Jake Forster
Requires-Python: >=3.9
License-Expression: MIT
Classifier: Topic :: Scientific/Engineering :: Medical Science Apps.
License-File: LICENSE
Requires-Dist: glowgreen
Requires-Dist: matplotlib
Requires-Dist: numpy
Requires-Dist: pandas
Requires-Dist: platformdirs
Requires-Dist: python-docx
Requires-Dist: scipy
Requires-Dist: xmltodict
Requires-Dist: cx_Freeze ; extra == "freeze"
Requires-Dist: pywin32 ; extra == "windows"
Project-URL: Changelog, https://github.com/SAMI-Medical-Physics/dorn/blob/main/CHANGELOG.md
Project-URL: Homepage, https://github.com/SAMI-Medical-Physics/dorn
Project-URL: Issues, https://github.com/SAMI-Medical-Physics/dorn/issues
Provides-Extra: freeze
Provides-Extra: windows
